amplabs/__init__.py
amplabs/app.py
amplabs/config.yaml
amplabs/assets/clientside_callback.js
amplabs/assets/custom.css
amplabs/assets/custom_editor.js
amplabs/assets/src-ace/ace.js
amplabs/assets/src-ace/ext-beautify.js
amplabs/assets/src-ace/ext-code_lens.js
amplabs/assets/src-ace/ext-command_bar.js
amplabs/assets/src-ace/ext-elastic_tabstops_lite.js
amplabs/assets/src-ace/ext-emmet.js
amplabs/assets/src-ace/ext-error_marker.js
amplabs/assets/src-ace/ext-hardwrap.js
amplabs/assets/src-ace/ext-inline_autocomplete.js
amplabs/assets/src-ace/ext-keybinding_menu.js
amplabs/assets/src-ace/ext-language_tools.js
amplabs/assets/src-ace/ext-linking.js
amplabs/assets/src-ace/ext-modelist.js
amplabs/assets/src-ace/ext-options.js
amplabs/assets/src-ace/ext-prompt.js
amplabs/assets/src-ace/ext-rtl.js
amplabs/assets/src-ace/ext-searchbox.js
amplabs/assets/src-ace/ext-settings_menu.js
amplabs/assets/src-ace/ext-simple_tokenizer.js
amplabs/assets/src-ace/ext-spellcheck.js
amplabs/assets/src-ace/ext-split.js
amplabs/assets/src-ace/ext-static_highlight.js
amplabs/assets/src-ace/ext-statusbar.js
amplabs/assets/src-ace/ext-textarea.js
amplabs/assets/src-ace/ext-themelist.js
amplabs/assets/src-ace/ext-whitespace.js
amplabs/assets/src-ace/keybinding-emacs.js
amplabs/assets/src-ace/keybinding-sublime.js
amplabs/assets/src-ace/keybinding-vim.js
amplabs/assets/src-ace/keybinding-vscode.js
amplabs/assets/src-ace/mode-yaml.js
amplabs/assets/src-ace/theme-xcode.js
amplabs/assets/src-ace/worker-yaml.js
amplabs/assets/src-ace/snippets/yaml.js
amplabs/callbacks/__init__.py
amplabs/callbacks/addAnnotation.py
amplabs/callbacks/addAxis.py
amplabs/callbacks/directoryTree.py
amplabs/callbacks/readFile.py
amplabs/callbacks/updateLayout.py
amplabs/callbacks/updateLineChart.py
amplabs/components/__init__.py
amplabs/components/appLayout.py
amplabs/components/axisSelection.py
amplabs/components/fileTree.py
amplabs/components/fileUpload.py
amplabs/components/graph.py
amplabs/utils/__init__.py
amplabs-0.2.1.dist-info/METADATA
amplabs-0.2.1.dist-info/WHEEL
amplabs-0.2.1.dist-info/top_level.txt
amplabs-0.2.1.dist-info/RECORD
