Metadata-Version: 2.1
Name: amplabs
Version: 0.2.1
Summary: One of the AmpLabs product to create high end plots for your data
Author: Amplabs
Requires-Dist: pandas
Requires-Dist: plotly ==5.22.0
Requires-Dist: dash
Requires-Dist: dash-bootstrap-components >=1.4.2
Requires-Dist: pyyaml <=6.0.1,>=6.0
Requires-Dist: dash-mantine-components >=0.14.0
Requires-Dist: dash-iconify
